{"data_mtime":1769764023,"dep_lines":[5,1,2,3,1,1,1,1,1,1,1,1,1,1,1,1,1,1,1,1,1,1,1,1,1,1,1],"dep_prios":[5,5,5,5,20,20,20,20,20,20,20,20,20,20,20,20,20,20,20,20,20,20,20,20,20,20,30],"dependencies":["ray.util.annotations","dataclasses","enum","typing","builtins","logging","opcode","abc","struct","types","os","platform","subprocess","itertools","dis","io","copyreg","pickle","warnings","weakref","sys","string","pyexpat.model","threading","uuid","pyexpat.errors","ray.util"],"hash":"d995f6138db361ae4e38fbda59c4c9d91e5e4c4b585d78df79746429d75aefbf","id":"ray.dashboard.modules.metrics.dashboards.common","ignore_all":true,"interface_hash":"906db3fb07d0b81b39d5ea2bb0767a21d46952661fe38bc417a0a3cae9354c9d","mtime":1768888792,"options":{"allow_redefinition":false,"allow_untyped_globals":false,"always_false":[],"always_true":[],"bazel":false,"check_untyped_defs":false,"disable_bytearray_promotion":false,"disable_error_code":[],"disable_memoryview_promotion":false,"disabled_error_codes":[],"disallow_any_decorated":false,"disallow_any_explicit":false,"disallow_any_expr":false,"disallow_any_generics":false,"disallow_any_unimported":false,"disallow_incomplete_defs":false,"disallow_subclassing_any":false,"disallow_untyped_calls":false,"disallow_untyped_decorators":false,"disallow_untyped_defs":false,"enable_error_code":[],"enabled_error_codes":[],"extra_checks":false,"follow_imports":"normal","follow_imports_for_stubs":false,"ignore_errors":false,"ignore_missing_imports":true,"implicit_optional":false,"implicit_reexport":true,"local_partial_types":false,"mypyc":false,"old_type_inference":false,"platform":"linux","plugins":[],"strict_concatenate":false,"strict_equality":false,"strict_optional":true,"warn_no_return":true,"warn_return_any":false,"warn_unreachable":false,"warn_unused_ignores":false},"path":"/home/kamau/bsopt/.venv/lib/python3.13/site-packages/ray/dashboard/modules/metrics/dashboards/common.py","plugin_data":null,"size":14119,"suppressed":[],"version_id":"1.9.0"}